powerline_pyenv/__init__.py
powerline_pyenv/segments.py
powerline_pyenv-0.1.3.dist-info/LICENSE.txt
powerline_pyenv-0.1.3.dist-info/WHEEL
powerline_pyenv-0.1.3.dist-info/METADATA
powerline_pyenv-0.1.3.dist-info/RECORD
