Metadata-Version: 2.1
Name: powerline-pyenv
Version: 0.1.3
Summary: A Powerline segment for showing pyenv version
License: MIT
Author: Sinkerine
Author-email: github@15cm.net
Requires-Python: >=2.7,<4
Classifier: License :: OSI Approved :: MIT License
Classifier: Programming Language :: Python :: 2
Classifier: Programming Language :: Python :: 2.7
Classifier: Programming Language :: Python :: 3
Classifier: Programming Language :: Python :: 3.4
Classifier: Programming Language :: Python :: 3.5
Classifier: Programming Language :: Python :: 3.6
Classifier: Programming Language :: Python :: 3.7
Requires-Dist: powerline-status (>=2.7,<3.0)
